{
  "links": [
    {
      "source": "66",
      "target": "27"
    },
    {
      "source": "45",
      "target": "1"
    },
    {
      "source": "73",
      "target": "32"
    },
    {
      "source": "69",
      "target": "42"
    },
    {
      "source": "76",
      "target": "65"
    },
    {
      "source": "2",
      "target": "18"
    },
    {
      "source": "66",
      "target": "20"
    },
    {
      "source": "48",
      "target": "55"
    },
    {
      "source": "26",
      "target": "40"
    },
    {
      "source": "74",
      "target": "59"
    },
    {
      "source": "37",
      "target": "64"
    },
    {
      "source": "12",
      "target": "16"
    },
    {
      "source": "15",
      "target": "36"
    },
    {
      "source": "23",
      "target": "12"
    },
    {
      "source": "63",
      "target": "64"
    },
    {
      "source": "32",
      "target": "61"
    },
    {
      "source": "23",
      "target": "30"
    },
    {
      "source": "25",
      "target": "30"
    },
    {
      "source": "68",
      "target": "40"
    },
    {
      "source": "38",
      "target": "75"
    },
    {
      "source": "24",
      "target": "38"
    },
    {
      "source": "75",
      "target": "41"
    },
    {
      "source": "74",
      "target": "51"
    },
    {
      "source": "33",
      "target": "15"
    },
    {
      "source": "16",
      "target": "22"
    },
    {
      "source": "20",
      "target": "39"
    },
    {
      "source": "45",
      "target": "39"
    },
    {
      "source": "30",
      "target": "5"
    },
    {
      "source": "1",
      "target": "71"
    },
    {
      "source": "54",
      "target": "42"
    },
    {
      "source": "41",
      "target": "70"
    },
    {
      "source": "46",
      "target": "66"
    },
    {
      "source": "54",
      "target": "53"
    },
    {
      "source": "40",
      "target": "48"
    },
    {
      "source": "46",
      "target": "49"
    },
    {
      "source": "9",
      "target": "14"
    },
    {
      "source": "42",
      "target": "7"
    },
    {
      "source": "51",
      "target": "7"
    },
    {
      "source": "30",
      "target": "34"
    },
    {
      "source": "78",
      "target": "50"
    },
    {
      "source": "78",
      "target": "13"
    },
    {
      "source": "47",
      "target": "40"
    },
    {
      "source": "50",
      "target": "40"
    },
    {
      "source": "41",
      "target": "65"
    },
    {
      "source": "18",
      "target": "25"
    },
    {
      "source": "75",
      "target": "5"
    },
    {
      "source": "61",
      "target": "40"
    },
    {
      "source": "8",
      "target": "22"
    },
    {
      "source": "27",
      "target": "38"
    },
    {
      "source": "53",
      "target": "35"
    },
    {
      "source": "22",
      "target": "36"
    },
    {
      "source": "59",
      "target": "22"
    },
    {
      "source": "77",
      "target": "64"
    },
    {
      "source": "48",
      "target": "54"
    },
    {
      "source": "29",
      "target": "24"
    },
    {
      "source": "23",
      "target": "33"
    },
    {
      "source": "4",
      "target": "21"
    },
    {
      "source": "42",
      "target": "61"
    },
    {
      "source": "66",
      "target": "46"
    },
    {
      "source": "53",
      "target": "18"
    },
    {
      "source": "34",
      "target": "17"
    },
    {
      "source": "47",
      "target": "17"
    }
  ],
  "nodes": [
    {
      "id": "1",
      "color": 0.11897391778858651,
      "size": 0.10694375052106286
    },
    {
      "id": "2",
      "color": 0.18573603154158314,
      "size": 0.11830413987247625
    },
    {
      "id": "3",
      "color": 0.1362341217753395,
      "size": 0.08125106349964359
    },
    {
      "id": "4",
      "color": 0.16591068922275892,
      "size": 0.08787507503868812
    },
    {
      "id": "5",
      "color": 0.15902460205175323,
      "size": 0.16200087893592752
    },
    {
      "id": "6",
      "color": 0.08547711427390457,
      "size": 0.09877653392269578
    },
    {
      "id": "7",
      "color": 0.1627948571316839,
      "size": 0.0835768693390347
    },
    {
      "id": "8",
      "color": 0.09787562650725729,
      "size": 0.12438446046080702
    },
    {
      "id": "9",
      "color": 0.09372270086890182,
      "size": 0.0927873704060312
    },
    {
      "id": "10",
      "color": 0.15737397222810776,
      "size": 0.11378510782125248
    },
    {
      "id": "11",
      "color": 0.14811002226523937,
      "size": 0.1388642043372898
    },
    {
      "id": "12",
      "color": 0.14300626197934377,
      "size": 0.15878195898657335
    },
    {
      "id": "13",
      "color": 0.1528154308788887,
      "size": 0.11848700702004476
    },
    {
      "id": "14",
      "color": 0.057269388196314455,
      "size": 0.14082192330994633
    },
    {
      "id": "15",
      "color": 0.08653104051075507,
      "size": 0.10200050249006562
    },
    {
      "id": "16",
      "color": 0.07447392236703314,
      "size": 0.12484748657866117
    },
    {
      "id": "17",
      "color": 0.07873563043849272,
      "size": 0.06975367123072128
    },
    {
      "id": "18",
      "color": 0.05404958805768648,
      "size": 0.1384023581531612
    },
    {
      "id": "19",
      "color": 0.06212283363745902,
      "size": 0.09405044982207686
    },
    {
      "id": "20",
      "color": 0.09126241580177676,
      "size": 0.06229681389080735
    },
    {
      "id": "21",
      "color": 0.11480143419570445,
      "size": 0.1328938626842453
    },
    {
      "id": "22",
      "color": 0.12711018370696905,
      "size": 0.10369577340953394
    },
    {
      "id": "23",
      "color": 0.05492145536203204,
      "size": 0.09710677034248005
    },
    {
      "id": "24",
      "color": 0.11653338579175188,
      "size": 0.10814375031096196
    },
    {
      "id": "25",
      "color": 0.07390965471133928,
      "size": 0.06716182349395027
    },
    {
      "id": "26",
      "color": 0.07524820103746717,
      "size": 0.10562195374976684
    },
    {
      "id": "27",
      "color": 0.11042851374285456,
      "size": 0.11882510987828383
    },
    {
      "id": "28",
      "color": 0.05400720958459327,
      "size": 0.061208261542649155
    },
    {
      "id": "29",
      "color": 0.08520426601991715,
      "size": 0.08834757540065387
    },
    {
      "id": "30",
      "color": 0.11593599216790945,
      "size": 0.0723643236941083
    },
    {
      "id": "31",
      "color": 0.11375095234008106,
      "size": 0.11421320221647568
    },
    {
      "id": "32",
      "color": 0.06402384706749316,
      "size": 0.10664779073051402
    },
    {
      "id": "33",
      "color": 0.04605573327704063,
      "size": 0.08930753447126792
    },
    {
      "id": "34",
      "color": 0.05205108494312592,
      "size": 0.0576962159771253
    },
    {
      "id": "35",
      "color": 0.05080444413454824,
      "size": 0.05620873075125719
    },
    {
      "id": "36",
      "color": 0.0359373262711905,
      "size": 0.09175709709633924
    },
    {
      "id": "37",
      "color": 0.03916229898688484,
      "size": 0.09788360772645195
    },
    {
      "id": "38",
      "color": 0.04756928361206434,
      "size": 0.054550501012359406
    },
    {
      "id": "39",
      "color": 0.09209816177745934,
      "size": 0.09612750810527695
    },
    {
      "id": "40",
      "color": 0.04279941935268124,
      "size": 0.057479709781277484
    },
    {
      "id": "41",
      "color": 0.0756231630233434,
      "size": 0.0764312320347207
    },
    {
      "id": "42",
      "color": 0.0773000432764778,
      "size": 0.036602294901169966
    },
    {
      "id": "43",
      "color": 0.06870241370126767,
      "size": 0.07206949519227374
    },
    {
      "id": "44",
      "color": 0.03191857767180713,
      "size": 0.03753433635791406
    },
    {
      "id": "45",
      "color": 0.06070755924345794,
      "size": 0.0404825594287487
    },
    {
      "id": "46",
      "color": 0.07601762460555145,
      "size": 0.05574897632362005
    },
    {
      "id": "47",
      "color": 0.029558073215865246,
      "size": 0.05514324899102168
    },
    {
      "id": "48",
      "color": 0.06241229670286646,
      "size": 0.06071868972955846
    },
    {
      "id": "49",
      "color": 0.05389520312494399,
      "size": 0.07150121814428717
    },
    {
      "id": "50",
      "color": 0.056584280434873235,
      "size": 0.047793799601575856
    },
    {
      "id": "51",
      "color": 0.03817230018810024,
      "size": 0.040302618374377874
    },
    {
      "id": "52",
      "color": 0.03438091713650059,
      "size": 0.059709259995042036
    },
    {
      "id": "53",
      "color": 0.047527957502495,
      "size": 0.02314817005218889
    },
    {
      "id": "54",
      "color": 0.022100665890466005,
      "size": 0.03008282107653093
    },
    {
      "id": "55",
      "color": 0.056526469437985866,
      "size": 0.04849292825607464
    },
    {
      "id": "56",
      "color": 0.03805433178122739,
      "size": 0.031128040542216812
    },
    {
      "id": "57",
      "color": 0.05187792304441989,
      "size": 0.04083002405600225
    },
    {
      "id": "58",
      "color": 0.01898311164084339,
      "size": 0.030932454471194647
    },
    {
      "id": "59",
      "color": 0.021445516741765126,
      "size": 0.017427355501247573
    },
    {
      "id": "60",
      "color": 0.032831415740986136,
      "size": 0.021022078076444475
    },
    {
      "id": "61",
      "color": 0.02581478927705422,
      "size": 0.02632544859773852
    },
    {
      "id": "62",
      "color": 0.03503697504487275,
      "size": 0.022861484834451416
    },
    {
      "id": "63",
      "color": 0.02469798285223681,
      "size": 0.02242363252719321
    },
    {
      "id": "64",
      "color": 0.012101977301962203,
      "size": 0.024275015148394356
    },
    {
      "id": "65",
      "color": 0.01284562724825972,
      "size": 0.019388628657907105
    },
    {
      "id": "66",
      "color": 0.009982504954933922,
      "size": 0.02026935272614571
    },
    {
      "id": "67",
      "color": 0.024007797227435686,
      "size": 0.021300280387096995
    },
    {
      "id": "68",
      "color": 0.01939377352313941,
      "size": 0.013022875826259987
    },
    {
      "id": "69",
      "color": 0.009870214676153942,
      "size": 0.020939935308054377
    },
    {
      "id": "70",
      "color": 0.01607218915714993,
      "size": 0.00933623880595461
    },
    {
      "id": "71",
      "color": 0.01601623015347463,
      "size": 0.008965622677860002
    },
    {
      "id": "72",
      "color": 0.007905333158093577,
      "size": 0.007803442743294999
    },
    {
      "id": "73",
      "color": 0.004922907181438127,
      "size": 0.0045010887404796085
    },
    {
      "id": "74",
      "color": 0.006813735958853759,
      "size": 0.004821766266694052
    },
    {
      "id": "75",
      "color": 0.003939664865304425,
      "size": 0.004817087446173725
    },
    {
      "id": "76",
      "color": 0.0037586737995713216,
      "size": 0.0041604362922662294
    },
    {
      "id": "77",
      "color": 0.0009279933107410077,
      "size": 0.0008581331093552474
    },
    {
      "id": "78",
      "color": 0.0,
      "size": 0.0
    }
  ]
}