{
  "links": [
    {
      "source": "2",
      "target": "8"
    },
    {
      "source": "5",
      "target": "12"
    },
    {
      "source": "8",
      "target": "11"
    },
    {
      "source": "13",
      "target": "4"
    },
    {
      "source": "3",
      "target": "10"
    },
    {
      "source": "5",
      "target": "7"
    },
    {
      "source": "13",
      "target": "6"
    },
    {
      "source": "1",
      "target": "10"
    },
    {
      "source": "5",
      "target": "1"
    },
    {
      "source": "7",
      "target": "9"
    }
  ],
  "nodes": [
    {
      "id": "1",
      "color": 0.02216235600886282,
      "size": 0.012341720523917195
    },
    {
      "id": "2",
      "color": 0.011914824629832569,
      "size": 0.021718818984733664
    },
    {
      "id": "3",
      "color": 0.013157348332858577,
      "size": 0.024267045088678413
    },
    {
      "id": "4",
      "color": 0.014611299691251876,
      "size": 0.01914198831302248
    },
    {
      "id": "5",
      "color": 0.011113437881820265,
      "size": 0.009747446874825691
    },
    {
      "id": "6",
      "color": 0.009010257082254934,
      "size": 0.015523546381063546
    },
    {
      "id": "7",
      "color": 0.013468411452770116,
      "size": 0.010509285056858546
    },
    {
      "id": "8",
      "color": 0.0092277118504525,
      "size": 0.012260011990499375
    },
    {
      "id": "9",
      "color": 0.010622011091942007,
      "size": 0.004025910719788019
    },
    {
      "id": "10",
      "color": 0.006308525911261742,
      "size": 0.004337545093851801
    },
    {
      "id": "11",
      "color": 0.003062658783813304,
      "size": 0.003158296256473034
    },
    {
      "id": "12",
      "color": 0.0024996788083550144,
      "size": 0.0011554390579947649
    },
    {
      "id": "13",
      "color": 0.0,
      "size": 0.0
    }
  ]
}