{
  "links": [
    {
      "source": "15",
      "target": "12"
    },
    {
      "source": "4",
      "target": "10"
    },
    {
      "source": "16",
      "target": "11"
    },
    {
      "source": "5",
      "target": "9"
    },
    {
      "source": "9",
      "target": "14"
    },
    {
      "source": "16",
      "target": "6"
    },
    {
      "source": "7",
      "target": "1"
    },
    {
      "source": "8",
      "target": "12"
    },
    {
      "source": "8",
      "target": "11"
    },
    {
      "source": "3",
      "target": "1"
    },
    {
      "source": "3",
      "target": "11"
    },
    {
      "source": "4",
      "target": "16"
    },
    {
      "source": "4",
      "target": "12"
    },
    {
      "source": "10",
      "target": "1"
    },
    {
      "source": "1",
      "target": "10"
    },
    {
      "source": "9",
      "target": "5"
    },
    {
      "source": "4",
      "target": "11"
    }
  ],
  "nodes": [
    {
      "id": "1",
      "color": 0.014907313559694884,
      "size": 0.01818680129576858
    },
    {
      "id": "2",
      "color": 0.01082927864449983,
      "size": 0.011525617214899333
    },
    {
      "id": "3",
      "color": 0.011932757724641963,
      "size": 0.010055173794735677
    },
    {
      "id": "4",
      "color": 0.011634846224682836,
      "size": 0.009882688634984997
    },
    {
      "id": "5",
      "color": 0.013754262468110682,
      "size": 0.0157352715259529
    },
    {
      "id": "6",
      "color": 0.012719112930839552,
      "size": 0.006462705017701035
    },
    {
      "id": "7",
      "color": 0.010043333598902577,
      "size": 0.01297941179523981
    },
    {
      "id": "8",
      "color": 0.006875221299658228,
      "size": 0.011398247523806254
    },
    {
      "id": "9",
      "color": 0.0055981582878576784,
      "size": 0.011427972774339695
    },
    {
      "id": "10",
      "color": 0.007030506470690406,
      "size": 0.009006713137085507
    },
    {
      "id": "11",
      "color": 0.005786452109787609,
      "size": 0.0049862230699780664
    },
    {
      "id": "12",
      "color": 0.0025977882668030542,
      "size": 0.00562189041557812
    },
    {
      "id": "13",
      "color": 0.0029558147964085933,
      "size": 0.0035068703812807874
    },
    {
      "id": "14",
      "color": 0.0016578401612108813,
      "size": 0.0020263445322187797
    },
    {
      "id": "15",
      "color": 0.002793270021050108,
      "size": 0.0019382338223372477
    },
    {
      "id": "16",
      "color": 0.0010860378524036598,
      "size": 0.0005148306354447706
    },
    {
      "id": "17",
      "color": 0.0,
      "size": 0.0
    }
  ]
}