{
  "links": [
    {
      "source": "13",
      "target": "22"
    },
    {
      "source": "42",
      "target": "5"
    },
    {
      "source": "14",
      "target": "37"
    },
    {
      "source": "41",
      "target": "9"
    },
    {
      "source": "22",
      "target": "40"
    },
    {
      "source": "31",
      "target": "57"
    },
    {
      "source": "38",
      "target": "27"
    },
    {
      "source": "18",
      "target": "8"
    },
    {
      "source": "7",
      "target": "11"
    },
    {
      "source": "25",
      "target": "23"
    },
    {
      "source": "63",
      "target": "60"
    },
    {
      "source": "6",
      "target": "36"
    },
    {
      "source": "44",
      "target": "52"
    },
    {
      "source": "52",
      "target": "53"
    },
    {
      "source": "40",
      "target": "33"
    },
    {
      "source": "55",
      "target": "22"
    },
    {
      "source": "30",
      "target": "9"
    },
    {
      "source": "46",
      "target": "39"
    },
    {
      "source": "39",
      "target": "7"
    },
    {
      "source": "66",
      "target": "33"
    },
    {
      "source": "31",
      "target": "49"
    },
    {
      "source": "56",
      "target": "35"
    },
    {
      "source": "35",
      "target": "50"
    },
    {
      "source": "28",
      "target": "52"
    },
    {
      "source": "13",
      "target": "29"
    },
    {
      "source": "48",
      "target": "52"
    },
    {
      "source": "33",
      "target": "64"
    },
    {
      "source": "67",
      "target": "35"
    },
    {
      "source": "71",
      "target": "65"
    },
    {
      "source": "17",
      "target": "32"
    },
    {
      "source": "26",
      "target": "54"
    },
    {
      "source": "56",
      "target": "36"
    },
    {
      "source": "24",
      "target": "57"
    },
    {
      "source": "63",
      "target": "22"
    },
    {
      "source": "25",
      "target": "34"
    },
    {
      "source": "19",
      "target": "20"
    },
    {
      "source": "67",
      "target": "69"
    },
    {
      "source": "61",
      "target": "7"
    },
    {
      "source": "57",
      "target": "36"
    },
    {
      "source": "65",
      "target": "55"
    },
    {
      "source": "55",
      "target": "29"
    },
    {
      "source": "44",
      "target": "25"
    },
    {
      "source": "21",
      "target": "62"
    },
    {
      "source": "6",
      "target": "67"
    },
    {
      "source": "7",
      "target": "30"
    },
    {
      "source": "25",
      "target": "33"
    },
    {
      "source": "73",
      "target": "50"
    },
    {
      "source": "16",
      "target": "46"
    },
    {
      "source": "9",
      "target": "71"
    }
  ],
  "nodes": [
    {
      "id": "1",
      "color": 0.09785297756108324,
      "size": 0.13455002504980207
    },
    {
      "id": "2",
      "color": 0.06935212644865317,
      "size": 0.07954540445904582
    },
    {
      "id": "3",
      "color": 0.11155832375667271,
      "size": 0.10789177606828841
    },
    {
      "id": "4",
      "color": 0.0855495774471501,
      "size": 0.057275567581809586
    },
    {
      "id": "5",
      "color": 0.08796097491753974,
      "size": 0.057017300215230174
    },
    {
      "id": "6",
      "color": 0.11357813356527244,
      "size": 0.09453880055035226
    },
    {
      "id": "7",
      "color": 0.06818252988671791,
      "size": 0.11710397446109651
    },
    {
      "id": "8",
      "color": 0.06677298051997435,
      "size": 0.12682341676784548
    },
    {
      "id": "9",
      "color": 0.103859561198979,
      "size": 0.1233141621405597
    },
    {
      "id": "10",
      "color": 0.07532631546054033,
      "size": 0.06545463549725493
    },
    {
      "id": "11",
      "color": 0.09301353556229348,
      "size": 0.11741999586132536
    },
    {
      "id": "12",
      "color": 0.06339485836287032,
      "size": 0.06106328130480096
    },
    {
      "id": "13",
      "color": 0.0621692089394514,
      "size": 0.05439007864266838
    },
    {
      "id": "14",
      "color": 0.044542573172023064,
      "size": 0.06555002790529485
    },
    {
      "id": "15",
      "color": 0.05213705191548379,
      "size": 0.09733330830116838
    },
    {
      "id": "16",
      "color": 0.0589220021418793,
      "size": 0.10007929434000484
    },
    {
      "id": "17",
      "color": 0.04756697499111951,
      "size": 0.06680141500965436
    },
    {
      "id": "18",
      "color": 0.051359950948201664,
      "size": 0.07705574116363918
    },
    {
      "id": "19",
      "color": 0.06373163306168135,
      "size": 0.08912715871891216
    },
    {
      "id": "20",
      "color": 0.10437259997390168,
      "size": 0.0447838704649464
    },
    {
      "id": "21",
      "color": 0.10418991318975493,
      "size": 0.0791697216824921
    },
    {
      "id": "22",
      "color": 0.06558852205089336,
      "size": 0.08216107717596333
    },
    {
      "id": "23",
      "color": 0.040382951771321146,
      "size": 0.09048772655301003
    },
    {
      "id": "24",
      "color": 0.08547381994830075,
      "size": 0.09833515125539624
    },
    {
      "id": "25",
      "color": 0.039257556326447125,
      "size": 0.09404885204838082
    },
    {
      "id": "26",
      "color": 0.10138103559999191,
      "size": 0.06642426051133024
    },
    {
      "id": "27",
      "color": 0.05355183636281331,
      "size": 0.07888861903969048
    },
    {
      "id": "28",
      "color": 0.07901156702543055,
      "size": 0.08155120132889009
    },
    {
      "id": "29",
      "color": 0.05936844214977527,
      "size": 0.03409710973721144
    },
    {
      "id": "30",
      "color": 0.09124736836997112,
      "size": 0.05074465253562464
    },
    {
      "id": "31",
      "color": 0.0352430082968235,
      "size": 0.07440396243549448
    },
    {
      "id": "32",
      "color": 0.08245960904802385,
      "size": 0.07851060551303271
    },
    {
      "id": "33",
      "color": 0.06225924325599788,
      "size": 0.048892319596150535
    },
    {
      "id": "34",
      "color": 0.030476035303910964,
      "size": 0.07136821916267135
    },
    {
      "id": "35",
      "color": 0.06970468885305978,
      "size": 0.07935945887285688
    },
    {
      "id": "36",
      "color": 0.03083627587184748,
      "size": 0.028817581775641633
    },
    {
      "id": "37",
      "color": 0.036366456602048,
      "size": 0.050274778984965046
    },
    {
      "id": "38",
      "color": 0.07252715770578992,
      "size": 0.055302389468911875
    },
    {
      "id": "39",
      "color": 0.04088129059473918,
      "size": 0.06732779589330287
    },
    {
      "id": "40",
      "color": 0.06601280791077603,
      "size": 0.04509096099952252
    },
    {
      "id": "41",
      "color": 0.0406136869842654,
      "size": 0.06765522833523989
    },
    {
      "id": "42",
      "color": 0.03155338836529992,
      "size": 0.03477311600439069
    },
    {
      "id": "43",
      "color": 0.03387806730099741,
      "size": 0.034243715757614666
    },
    {
      "id": "44",
      "color": 0.027678623913813205,
      "size": 0.03632334893347348
    },
    {
      "id": "45",
      "color": 0.03704580090589521,
      "size": 0.05268185760021071
    },
    {
      "id": "46",
      "color": 0.049321388265022734,
      "size": 0.04230277587826147
    },
    {
      "id": "47",
      "color": 0.04069034562943001,
      "size": 0.04090903840957127
    },
    {
      "id": "48",
      "color": 0.02686838642306576,
      "size": 0.037136322530368714
    },
    {
      "id": "49",
      "color": 0.036198041767006944,
      "size": 0.019921780665634558
    },
    {
      "id": "50",
      "color": 0.037748201432051535,
      "size": 0.024154820609036926
    },
    {
      "id": "51",
      "color": 0.04517491432181909,
      "size": 0.03703117344084136
    },
    {
      "id": "52",
      "color": 0.016138195025068997,
      "size": 0.032012136788636195
    },
    {
      "id": "53",
      "color": 0.017287623974983873,
      "size": 0.037102325316975805
    },
    {
      "id": "54",
      "color": 0.013844244160316148,
      "size": 0.03357046856802145
    },
    {
      "id": "55",
      "color": 0.020684088722190287,
      "size": 0.02298839108286714
    },
    {
      "id": "56",
      "color": 0.033141931612963325,
      "size": 0.026698906597108885
    },
    {
      "id": "57",
      "color": 0.014839268657470537,
      "size": 0.02725978492938563
    },
    {
      "id": "58",
      "color": 0.013318877401608106,
      "size": 0.025661004904820945
    },
    {
      "id": "59",
      "color": 0.01691412828319924,
      "size": 0.020375928476834435
    },
    {
      "id": "60",
      "color": 0.015380377531265282,
      "size": 0.01755838689815795
    },
    {
      "id": "61",
      "color": 0.0215359882796275,
      "size": 0.01886329825223144
    },
    {
      "id": "62",
      "color": 0.01915866370875538,
      "size": 0.015062809952860103
    },
    {
      "id": "63",
      "color": 0.010095263100961517,
      "size": 0.01573904964617062
    },
    {
      "id": "64",
      "color": 0.014500350183799814,
      "size": 0.008288311134042103
    },
    {
      "id": "65",
      "color": 0.0070482530911211635,
      "size": 0.006680332935923194
    },
    {
      "id": "66",
      "color": 0.011812021232969172,
      "size": 0.01288638469809761
    },
    {
      "id": "67",
      "color": 0.009461561589345049,
      "size": 0.007265715034317125
    },
    {
      "id": "68",
      "color": 0.004381249496241377,
      "size": 0.008138307055086827
    },
    {
      "id": "69",
      "color": 0.00721690626234164,
      "size": 0.005850850657323269
    },
    {
      "id": "70",
      "color": 0.0023409558114669384,
      "size": 0.005724800001375716
    },
    {
      "id": "71",
      "color": 0.0036156562508768237,
      "size": 0.003294329836645204
    },
    {
      "id": "72",
      "color": 0.0013474211090723856,
      "size": 0.0009768883078084061
    },
    {
      "id": "73",
      "color": 0.0,
      "size": 0.0
    }
  ]
}