{
  "links": [
    {
      "source": "22",
      "target": "20"
    },
    {
      "source": "11",
      "target": "10"
    },
    {
      "source": "6",
      "target": "18"
    },
    {
      "source": "8",
      "target": "13"
    },
    {
      "source": "26",
      "target": "1"
    },
    {
      "source": "7",
      "target": "24"
    },
    {
      "source": "4",
      "target": "14"
    },
    {
      "source": "26",
      "target": "9"
    },
    {
      "source": "3",
      "target": "8"
    },
    {
      "source": "14",
      "target": "12"
    },
    {
      "source": "5",
      "target": "20"
    },
    {
      "source": "12",
      "target": "4"
    },
    {
      "source": "7",
      "target": "5"
    },
    {
      "source": "9",
      "target": "17"
    },
    {
      "source": "4",
      "target": "26"
    },
    {
      "source": "3",
      "target": "7"
    },
    {
      "source": "9",
      "target": "24"
    },
    {
      "source": "26",
      "target": "19"
    },
    {
      "source": "3",
      "target": "14"
    }
  ],
  "nodes": [
    {
      "id": "1",
      "color": 0.05706826912933121,
      "size": 0.049500836225904156
    },
    {
      "id": "2",
      "color": 0.040265612174875606,
      "size": 0.054054161090842795
    },
    {
      "id": "3",
      "color": 0.019403666504491414,
      "size": 0.05665826340211082
    },
    {
      "id": "4",
      "color": 0.04653611946876008,
      "size": 0.03955686544342466
    },
    {
      "id": "5",
      "color": 0.024927754315202222,
      "size": 0.017759212089612453
    },
    {
      "id": "6",
      "color": 0.036940870431636484,
      "size": 0.022359606681625666
    },
    {
      "id": "7",
      "color": 0.018637598843327156,
      "size": 0.03872430621765578
    },
    {
      "id": "8",
      "color": 0.017919425840905827,
      "size": 0.03217434074081601
    },
    {
      "id": "9",
      "color": 0.02757790271284182,
      "size": 0.020614837170098967
    },
    {
      "id": "10",
      "color": 0.03677262719199673,
      "size": 0.019390717002898575
    },
    {
      "id": "11",
      "color": 0.03826225518873247,
      "size": 0.022958905190621135
    },
    {
      "id": "12",
      "color": 0.03094926513752902,
      "size": 0.033431290426869244
    },
    {
      "id": "13",
      "color": 0.03074484685890541,
      "size": 0.017031467826825842
    },
    {
      "id": "14",
      "color": 0.02096954651716947,
      "size": 0.024953946302004017
    },
    {
      "id": "15",
      "color": 0.011856258120957582,
      "size": 0.019848330311966388
    },
    {
      "id": "16",
      "color": 0.013999949151706919,
      "size": 0.023322293772414425
    },
    {
      "id": "17",
      "color": 0.010081667592954213,
      "size": 0.013912924310659753
    },
    {
      "id": "18",
      "color": 0.019545142206527522,
      "size": 0.015916368441237602
    },
    {
      "id": "19",
      "color": 0.017471915134316705,
      "size": 0.014552160166364448
    },
    {
      "id": "20",
      "color": 0.009403394245256772,
      "size": 0.014480028333216651
    },
    {
      "id": "21",
      "color": 0.006970823832435625,
      "size": 0.009231419422601356
    },
    {
      "id": "22",
      "color": 0.0041828921642458475,
      "size": 0.009749856043540301
    },
    {
      "id": "23",
      "color": 0.008231472319316677,
      "size": 0.00867463516930192
    },
    {
      "id": "24",
      "color": 0.00470784959208253,
      "size": 0.003113107295705216
    },
    {
      "id": "25",
      "color": 0.0038190478832493186,
      "size": 0.003089030268745983
    },
    {
      "id": "26",
      "color": 0.0012930663355247968,
      "size": 0.0016820184855597308
    },
    {
      "id": "27",
      "color": 0.0,
      "size": 0.0
    }
  ]
}