{
  "links": [
    {
      "source": "2",
      "target": "14"
    },
    {
      "source": "5",
      "target": "16"
    },
    {
      "source": "8",
      "target": "10"
    },
    {
      "source": "9",
      "target": "16"
    },
    {
      "source": "12",
      "target": "4"
    },
    {
      "source": "9",
      "target": "6"
    },
    {
      "source": "2",
      "target": "15"
    },
    {
      "source": "8",
      "target": "16"
    },
    {
      "source": "7",
      "target": "8"
    },
    {
      "source": "6",
      "target": "14"
    }
  ],
  "nodes": [
    {
      "id": "1",
      "color": 0.015957522328362245,
      "size": 0.03625050712425556
    },
    {
      "id": "2",
      "color": 0.029326156192627004,
      "size": 0.013739476191899514
    },
    {
      "id": "3",
      "color": 0.017545979636220285,
      "size": 0.014855389858820452
    },
    {
      "id": "4",
      "color": 0.022984350732819413,
      "size": 0.014537183381271527
    },
    {
      "id": "5",
      "color": 0.022611753584984413,
      "size": 0.014053757191292473
    },
    {
      "id": "6",
      "color": 0.023245121337091473,
      "size": 0.012784817228476297
    },
    {
      "id": "7",
      "color": 0.021003408081367532,
      "size": 0.009365388115900418
    },
    {
      "id": "8",
      "color": 0.019767919268116354,
      "size": 0.007754859512463155
    },
    {
      "id": "9",
      "color": 0.0088038809747974,
      "size": 0.01132791587067332
    },
    {
      "id": "10",
      "color": 0.01232279240559066,
      "size": 0.010532431998395583
    },
    {
      "id": "11",
      "color": 0.012038558356407174,
      "size": 0.009646783358425077
    },
    {
      "id": "12",
      "color": 0.009978814595648049,
      "size": 0.010101041497701755
    },
    {
      "id": "13",
      "color": 0.004290590810651366,
      "size": 0.006240433558072259
    },
    {
      "id": "14",
      "color": 0.002351370363545442,
      "size": 0.0033791476268268737
    },
    {
      "id": "15",
      "color": 0.0012126830713417088,
      "size": 0.0021235166855355526
    },
    {
      "id": "16",
      "color": 0.0,
      "size": 0.0
    }
  ]
}