{
  "links": [
    {
      "source": "15",
      "target": "27"
    },
    {
      "source": "46",
      "target": "51"
    },
    {
      "source": "59",
      "target": "12"
    },
    {
      "source": "1",
      "target": "17"
    },
    {
      "source": "33",
      "target": "36"
    },
    {
      "source": "36",
      "target": "46"
    },
    {
      "source": "32",
      "target": "37"
    },
    {
      "source": "44",
      "target": "30"
    },
    {
      "source": "11",
      "target": "52"
    },
    {
      "source": "59",
      "target": "8"
    },
    {
      "source": "51",
      "target": "32"
    },
    {
      "source": "26",
      "target": "39"
    },
    {
      "source": "31",
      "target": "32"
    },
    {
      "source": "43",
      "target": "11"
    },
    {
      "source": "57",
      "target": "31"
    },
    {
      "source": "27",
      "target": "56"
    },
    {
      "source": "59",
      "target": "6"
    },
    {
      "source": "33",
      "target": "6"
    },
    {
      "source": "53",
      "target": "6"
    },
    {
      "source": "44",
      "target": "42"
    },
    {
      "source": "22",
      "target": "28"
    },
    {
      "source": "48",
      "target": "45"
    },
    {
      "source": "25",
      "target": "22"
    },
    {
      "source": "8",
      "target": "25"
    },
    {
      "source": "49",
      "target": "40"
    },
    {
      "source": "17",
      "target": "19"
    },
    {
      "source": "52",
      "target": "21"
    },
    {
      "source": "44",
      "target": "6"
    },
    {
      "source": "55",
      "target": "2"
    },
    {
      "source": "27",
      "target": "13"
    },
    {
      "source": "27",
      "target": "4"
    },
    {
      "source": "53",
      "target": "12"
    },
    {
      "source": "50",
      "target": "20"
    },
    {
      "source": "8",
      "target": "47"
    },
    {
      "source": "56",
      "target": "41"
    },
    {
      "source": "44",
      "target": "21"
    },
    {
      "source": "47",
      "target": "25"
    },
    {
      "source": "7",
      "target": "44"
    },
    {
      "source": "48",
      "target": "30"
    },
    {
      "source": "21",
      "target": "22"
    },
    {
      "source": "32",
      "target": "56"
    },
    {
      "source": "11",
      "target": "41"
    },
    {
      "source": "11",
      "target": "3"
    },
    {
      "source": "29",
      "target": "32"
    },
    {
      "source": "55",
      "target": "14"
    },
    {
      "source": "34",
      "target": "17"
    }
  ],
  "nodes": [
    {
      "id": "1",
      "color": 0.03977976382705351,
      "size": 0.05424643762304951
    },
    {
      "id": "2",
      "color": 0.050501023455034696,
      "size": 0.03031428518679601
    },
    {
      "id": "3",
      "color": 0.06150920339134005,
      "size": 0.03202724441567518
    },
    {
      "id": "4",
      "color": 0.03817987930323832,
      "size": 0.047914443034640715
    },
    {
      "id": "5",
      "color": 0.024821878111276285,
      "size": 0.06736300346093022
    },
    {
      "id": "6",
      "color": 0.0380609832452765,
      "size": 0.04445959214583089
    },
    {
      "id": "7",
      "color": 0.05646489123686187,
      "size": 0.032030544096430205
    },
    {
      "id": "8",
      "color": 0.02294504598280511,
      "size": 0.05541904626185927
    },
    {
      "id": "9",
      "color": 0.040959454858926506,
      "size": 0.03655849780165671
    },
    {
      "id": "10",
      "color": 0.03997197085819436,
      "size": 0.06083233821793922
    },
    {
      "id": "11",
      "color": 0.03789398405285397,
      "size": 0.03637964654803743
    },
    {
      "id": "12",
      "color": 0.028929789021318906,
      "size": 0.03456230816956292
    },
    {
      "id": "13",
      "color": 0.026169588112953987,
      "size": 0.02547157132580904
    },
    {
      "id": "14",
      "color": 0.050964131322610386,
      "size": 0.03970687515135736
    },
    {
      "id": "15",
      "color": 0.03506860334461504,
      "size": 0.0330450728822434
    },
    {
      "id": "16",
      "color": 0.03338115671017299,
      "size": 0.029278139765097206
    },
    {
      "id": "17",
      "color": 0.050416985686581595,
      "size": 0.02332714967601191
    },
    {
      "id": "18",
      "color": 0.05034152835368663,
      "size": 0.01910845129008573
    },
    {
      "id": "19",
      "color": 0.043396775976847476,
      "size": 0.02245855686435569
    },
    {
      "id": "20",
      "color": 0.02766454960766674,
      "size": 0.025961012859990446
    },
    {
      "id": "21",
      "color": 0.024888726121887916,
      "size": 0.04406519897302619
    },
    {
      "id": "22",
      "color": 0.025332457205898717,
      "size": 0.017221094731278756
    },
    {
      "id": "23",
      "color": 0.035874020671846835,
      "size": 0.04502737882652715
    },
    {
      "id": "24",
      "color": 0.04269637744415876,
      "size": 0.040750711949445094
    },
    {
      "id": "25",
      "color": 0.020402271846852196,
      "size": 0.021046978512260887
    },
    {
      "id": "26",
      "color": 0.018821007038044926,
      "size": 0.028180262980645025
    },
    {
      "id": "27",
      "color": 0.03565062760782016,
      "size": 0.013955635583647754
    },
    {
      "id": "28",
      "color": 0.016911215284820338,
      "size": 0.028448537466450066
    },
    {
      "id": "29",
      "color": 0.02698105996737077,
      "size": 0.03588691958079628
    },
    {
      "id": "30",
      "color": 0.02575329153834391,
      "size": 0.017024166770080163
    },
    {
      "id": "31",
      "color": 0.02995900048807897,
      "size": 0.023732895538500415
    },
    {
      "id": "32",
      "color": 0.031082539174492017,
      "size": 0.021140122592412304
    },
    {
      "id": "33",
      "color": 0.015393409811708253,
      "size": 0.01953409680312187
    },
    {
      "id": "34",
      "color": 0.021507969223905986,
      "size": 0.021991957671018008
    },
    {
      "id": "35",
      "color": 0.029725674913654784,
      "size": 0.021188772214281434
    },
    {
      "id": "36",
      "color": 0.02389351274548674,
      "size": 0.022976743750385383
    },
    {
      "id": "37",
      "color": 0.02606075886987657,
      "size": 0.011300450399278131
    },
    {
      "id": "38",
      "color": 0.024980302428689875,
      "size": 0.017760892908364367
    },
    {
      "id": "39",
      "color": 0.013085907487330418,
      "size": 0.010482622986680378
    },
    {
      "id": "40",
      "color": 0.021739501156547866,
      "size": 0.0217818876395429
    },
    {
      "id": "41",
      "color": 0.016445062131909258,
      "size": 0.021538899175143088
    },
    {
      "id": "42",
      "color": 0.01699636508456709,
      "size": 0.014046092585455515
    },
    {
      "id": "43",
      "color": 0.014760810138155417,
      "size": 0.009384633031283469
    },
    {
      "id": "44",
      "color": 0.012349353928056545,
      "size": 0.007233043525495036
    },
    {
      "id": "45",
      "color": 0.014319496294368662,
      "size": 0.0061973940478765545
    },
    {
      "id": "46",
      "color": 0.014226896656532241,
      "size": 0.014666762848357938
    },
    {
      "id": "47",
      "color": 0.013631742003267232,
      "size": 0.009382426995265996
    },
    {
      "id": "48",
      "color": 0.012312720686738261,
      "size": 0.009388051934359013
    },
    {
      "id": "49",
      "color": 0.007696115288162306,
      "size": 0.007729435499844452
    },
    {
      "id": "50",
      "color": 0.00643421547551722,
      "size": 0.00588394900058014
    },
    {
      "id": "51",
      "color": 0.00890099123634721,
      "size": 0.005181187827833645
    },
    {
      "id": "52",
      "color": 0.0061990217027729656,
      "size": 0.005395200365646994
    },
    {
      "id": "53",
      "color": 0.0056955346238094055,
      "size": 0.005585896618673285
    },
    {
      "id": "54",
      "color": 0.006299518405565186,
      "size": 0.004855558971868886
    },
    {
      "id": "55",
      "color": 0.003860703718103759,
      "size": 0.0036592548030536767
    },
    {
      "id": "56",
      "color": 0.0030338094533932016,
      "size": 0.0018989692254197431
    },
    {
      "id": "57",
      "color": 0.0021216256025623067,
      "size": 0.0010942192025818656
    },
    {
      "id": "58",
      "color": 0.0009196116446097897,
      "size": 0.0010204653171533178
    },
    {
      "id": "59",
      "color": 0.0,
      "size": 0.0
    }
  ]
}