{
  "links": [
    {
      "source": "27",
      "target": "52"
    },
    {
      "source": "21",
      "target": "28"
    },
    {
      "source": "35",
      "target": "1"
    },
    {
      "source": "36",
      "target": "17"
    },
    {
      "source": "59",
      "target": "51"
    },
    {
      "source": "17",
      "target": "20"
    },
    {
      "source": "7",
      "target": "16"
    },
    {
      "source": "1",
      "target": "6"
    },
    {
      "source": "16",
      "target": "47"
    },
    {
      "source": "56",
      "target": "12"
    },
    {
      "source": "53",
      "target": "24"
    },
    {
      "source": "54",
      "target": "30"
    },
    {
      "source": "4",
      "target": "42"
    },
    {
      "source": "42",
      "target": "17"
    },
    {
      "source": "43",
      "target": "37"
    },
    {
      "source": "40",
      "target": "23"
    },
    {
      "source": "16",
      "target": "3"
    },
    {
      "source": "44",
      "target": "12"
    },
    {
      "source": "21",
      "target": "34"
    },
    {
      "source": "50",
      "target": "39"
    },
    {
      "source": "59",
      "target": "39"
    },
    {
      "source": "29",
      "target": "22"
    },
    {
      "source": "59",
      "target": "17"
    },
    {
      "source": "39",
      "target": "16"
    },
    {
      "source": "31",
      "target": "25"
    },
    {
      "source": "6",
      "target": "58"
    },
    {
      "source": "14",
      "target": "23"
    },
    {
      "source": "52",
      "target": "45"
    },
    {
      "source": "45",
      "target": "10"
    },
    {
      "source": "48",
      "target": "3"
    },
    {
      "source": "12",
      "target": "25"
    },
    {
      "source": "53",
      "target": "8"
    },
    {
      "source": "23",
      "target": "53"
    },
    {
      "source": "50",
      "target": "51"
    },
    {
      "source": "58",
      "target": "17"
    },
    {
      "source": "40",
      "target": "16"
    },
    {
      "source": "35",
      "target": "27"
    },
    {
      "source": "29",
      "target": "16"
    },
    {
      "source": "38",
      "target": "46"
    },
    {
      "source": "34",
      "target": "16"
    },
    {
      "source": "24",
      "target": "40"
    },
    {
      "source": "56",
      "target": "28"
    },
    {
      "source": "41",
      "target": "34"
    },
    {
      "source": "3",
      "target": "1"
    },
    {
      "source": "45",
      "target": "59"
    },
    {
      "source": "58",
      "target": "40"
    },
    {
      "source": "25",
      "target": "59"
    },
    {
      "source": "56",
      "target": "55"
    },
    {
      "source": "7",
      "target": "17"
    },
    {
      "source": "10",
      "target": "55"
    },
    {
      "source": "14",
      "target": "41"
    },
    {
      "source": "36",
      "target": "20"
    },
    {
      "source": "28",
      "target": "25"
    }
  ],
  "nodes": [
    {
      "id": "1",
      "color": 0.051145901404707594,
      "size": 0.07062571637861852
    },
    {
      "id": "2",
      "color": 0.053400275743446426,
      "size": 0.0598078419722283
    },
    {
      "id": "3",
      "color": 0.07603778384230224,
      "size": 0.04770381350755154
    },
    {
      "id": "4",
      "color": 0.036419318651140335,
      "size": 0.07040997931080685
    },
    {
      "id": "5",
      "color": 0.08931831045517946,
      "size": 0.05081086384604881
    },
    {
      "id": "6",
      "color": 0.04519413450763397,
      "size": 0.07969389822454398
    },
    {
      "id": "7",
      "color": 0.040507410644243534,
      "size": 0.04586202232618929
    },
    {
      "id": "8",
      "color": 0.08513790025076053,
      "size": 0.047497468665020776
    },
    {
      "id": "9",
      "color": 0.06684622822532464,
      "size": 0.0413911354144248
    },
    {
      "id": "10",
      "color": 0.05259789480474871,
      "size": 0.0338395063121415
    },
    {
      "id": "11",
      "color": 0.02702416769800496,
      "size": 0.06861984111196262
    },
    {
      "id": "12",
      "color": 0.05572951626833627,
      "size": 0.05496655881831734
    },
    {
      "id": "13",
      "color": 0.028540581312831225,
      "size": 0.05551426057588624
    },
    {
      "id": "14",
      "color": 0.0615622941403634,
      "size": 0.035480614464082724
    },
    {
      "id": "15",
      "color": 0.037169348730016566,
      "size": 0.059450090986675704
    },
    {
      "id": "16",
      "color": 0.06637574802889755,
      "size": 0.058076891427399045
    },
    {
      "id": "17",
      "color": 0.06187265662970576,
      "size": 0.05809210442304368
    },
    {
      "id": "18",
      "color": 0.02861662470251693,
      "size": 0.06503867518787178
    },
    {
      "id": "19",
      "color": 0.06704506601039267,
      "size": 0.04332871566418754
    },
    {
      "id": "20",
      "color": 0.04492137380714256,
      "size": 0.055779515802935796
    },
    {
      "id": "21",
      "color": 0.06141871571878033,
      "size": 0.03835684305926007
    },
    {
      "id": "22",
      "color": 0.027805910170260937,
      "size": 0.02658819631443335
    },
    {
      "id": "23",
      "color": 0.02835067359126909,
      "size": 0.04144666553028765
    },
    {
      "id": "24",
      "color": 0.049789178865646294,
      "size": 0.04001081336282038
    },
    {
      "id": "25",
      "color": 0.0473699993195094,
      "size": 0.05199611260170688
    },
    {
      "id": "26",
      "color": 0.053295142998552855,
      "size": 0.031640596372417465
    },
    {
      "id": "27",
      "color": 0.025329917146660608,
      "size": 0.023538673856418352
    },
    {
      "id": "28",
      "color": 0.04349176324246646,
      "size": 0.025128996032218163
    },
    {
      "id": "29",
      "color": 0.024918678454433907,
      "size": 0.028817437718457094
    },
    {
      "id": "30",
      "color": 0.018842981904510097,
      "size": 0.03244291321402655
    },
    {
      "id": "31",
      "color": 0.017245407800540676,
      "size": 0.04129315438147465
    },
    {
      "id": "32",
      "color": 0.016637799656894495,
      "size": 0.015273378115835234
    },
    {
      "id": "33",
      "color": 0.01487750382331569,
      "size": 0.0384873577913928
    },
    {
      "id": "34",
      "color": 0.016779201970106076,
      "size": 0.026306809668210675
    },
    {
      "id": "35",
      "color": 0.014217299145532736,
      "size": 0.028605333740948966
    },
    {
      "id": "36",
      "color": 0.03457772919369433,
      "size": 0.02397563447566073
    },
    {
      "id": "37",
      "color": 0.028010579874031456,
      "size": 0.030916989673922726
    },
    {
      "id": "38",
      "color": 0.024940166628847203,
      "size": 0.0305452473585802
    },
    {
      "id": "39",
      "color": 0.024186235711639196,
      "size": 0.012317985105171849
    },
    {
      "id": "40",
      "color": 0.02660978638004342,
      "size": 0.020554970652359193
    },
    {
      "id": "41",
      "color": 0.028018217356467683,
      "size": 0.02213223578968495
    },
    {
      "id": "42",
      "color": 0.015955400135033996,
      "size": 0.02327630693127161
    },
    {
      "id": "43",
      "color": 0.01552207456591912,
      "size": 0.012880244296458794
    },
    {
      "id": "44",
      "color": 0.023452465593813806,
      "size": 0.011408955051622026
    },
    {
      "id": "45",
      "color": 0.022713850906749367,
      "size": 0.011985137990175473
    },
    {
      "id": "46",
      "color": 0.01773890256226289,
      "size": 0.021460867522547465
    },
    {
      "id": "47",
      "color": 0.014414977158359786,
      "size": 0.019634867855147325
    },
    {
      "id": "48",
      "color": 0.01805416185162729,
      "size": 0.007730391213868192
    },
    {
      "id": "49",
      "color": 0.012896487863065038,
      "size": 0.005811035442358378
    },
    {
      "id": "50",
      "color": 0.012589604381680875,
      "size": 0.014161650595471363
    },
    {
      "id": "51",
      "color": 0.011066705325091252,
      "size": 0.0052920830134408105
    },
    {
      "id": "52",
      "color": 0.008389555953617001,
      "size": 0.010879998662182191
    },
    {
      "id": "53",
      "color": 0.005889858091069384,
      "size": 0.007483760950752702
    },
    {
      "id": "54",
      "color": 0.004681798354919111,
      "size": 0.006074546505554627
    },
    {
      "id": "55",
      "color": 0.0027580435603480323,
      "size": 0.005810623072937589
    },
    {
      "id": "56",
      "color": 0.003852671752483831,
      "size": 0.0049273143460515775
    },
    {
      "id": "57",
      "color": 0.002830106910238828,
      "size": 0.001535415276055617
    },
    {
      "id": "58",
      "color": 0.0005662899034657048,
      "size": 0.0007970066806542781
    },
    {
      "id": "59",
      "color": 0.0,
      "size": 0.0
    }
  ]
}