{
  "links": [
    {
      "source": "2",
      "target": "18"
    },
    {
      "source": "19",
      "target": "4"
    },
    {
      "source": "21",
      "target": "16"
    },
    {
      "source": "1",
      "target": "29"
    },
    {
      "source": "23",
      "target": "45"
    },
    {
      "source": "17",
      "target": "46"
    },
    {
      "source": "13",
      "target": "21"
    },
    {
      "source": "33",
      "target": "3"
    },
    {
      "source": "26",
      "target": "29"
    },
    {
      "source": "49",
      "target": "32"
    },
    {
      "source": "36",
      "target": "49"
    },
    {
      "source": "35",
      "target": "33"
    },
    {
      "source": "17",
      "target": "2"
    },
    {
      "source": "33",
      "target": "39"
    },
    {
      "source": "50",
      "target": "8"
    },
    {
      "source": "17",
      "target": "14"
    },
    {
      "source": "5",
      "target": "29"
    },
    {
      "source": "40",
      "target": "1"
    },
    {
      "source": "43",
      "target": "31"
    },
    {
      "source": "16",
      "target": "23"
    },
    {
      "source": "11",
      "target": "26"
    },
    {
      "source": "34",
      "target": "16"
    },
    {
      "source": "4",
      "target": "6"
    },
    {
      "source": "37",
      "target": "24"
    },
    {
      "source": "32",
      "target": "43"
    },
    {
      "source": "12",
      "target": "4"
    },
    {
      "source": "45",
      "target": "50"
    },
    {
      "source": "9",
      "target": "5"
    },
    {
      "source": "30",
      "target": "50"
    },
    {
      "source": "45",
      "target": "10"
    }
  ],
  "nodes": [
    {
      "id": "1",
      "color": 0.02557712691186728,
      "size": 0.05091211289024449
    },
    {
      "id": "2",
      "color": 0.060974454198846784,
      "size": 0.04536296121492257
    },
    {
      "id": "3",
      "color": 0.05446457749160089,
      "size": 0.03329104675330942
    },
    {
      "id": "4",
      "color": 0.024069277578462153,
      "size": 0.06347969129252547
    },
    {
      "id": "5",
      "color": 0.0380158505238316,
      "size": 0.025169459057485608
    },
    {
      "id": "6",
      "color": 0.05212103031818598,
      "size": 0.061863117096759915
    },
    {
      "id": "7",
      "color": 0.058761600208633157,
      "size": 0.04034763008572102
    },
    {
      "id": "8",
      "color": 0.054937880407227926,
      "size": 0.03300554034136218
    },
    {
      "id": "9",
      "color": 0.06033081111496398,
      "size": 0.026693006831856676
    },
    {
      "id": "10",
      "color": 0.04459017182042738,
      "size": 0.020410802095250886
    },
    {
      "id": "11",
      "color": 0.039204253666595926,
      "size": 0.05027442706304163
    },
    {
      "id": "12",
      "color": 0.05168916640320264,
      "size": 0.026977946818144388
    },
    {
      "id": "13",
      "color": 0.051400930057471116,
      "size": 0.03659171537567252
    },
    {
      "id": "14",
      "color": 0.037770569189925884,
      "size": 0.030750900587383157
    },
    {
      "id": "15",
      "color": 0.04636024552546957,
      "size": 0.044807912803128756
    },
    {
      "id": "16",
      "color": 0.02340668479142069,
      "size": 0.030590696680692184
    },
    {
      "id": "17",
      "color": 0.04751635042493326,
      "size": 0.0378734388369483
    },
    {
      "id": "18",
      "color": 0.02494933979582977,
      "size": 0.02501215163842008
    },
    {
      "id": "19",
      "color": 0.02928355261703277,
      "size": 0.04277832583065313
    },
    {
      "id": "20",
      "color": 0.04145207214195773,
      "size": 0.02533059812554589
    },
    {
      "id": "21",
      "color": 0.03875901874812563,
      "size": 0.024229677818592473
    },
    {
      "id": "22",
      "color": 0.031126289805684593,
      "size": 0.03990155084408749
    },
    {
      "id": "23",
      "color": 0.030500132555282278,
      "size": 0.031681242307053534
    },
    {
      "id": "24",
      "color": 0.026297244859697852,
      "size": 0.026418814766305893
    },
    {
      "id": "25",
      "color": 0.024681308553203694,
      "size": 0.028425214488266494
    },
    {
      "id": "26",
      "color": 0.030672089564141705,
      "size": 0.026605177657425816
    },
    {
      "id": "27",
      "color": 0.01323992614281396,
      "size": 0.019227215561602454
    },
    {
      "id": "28",
      "color": 0.03180273086042213,
      "size": 0.01647076686885921
    },
    {
      "id": "29",
      "color": 0.02234396276843006,
      "size": 0.014317240913109349
    },
    {
      "id": "30",
      "color": 0.02488850113577627,
      "size": 0.023418055347202378
    },
    {
      "id": "31",
      "color": 0.027954406802806704,
      "size": 0.012174863857577236
    },
    {
      "id": "32",
      "color": 0.022207028659729355,
      "size": 0.015712834346449676
    },
    {
      "id": "33",
      "color": 0.02533077600254385,
      "size": 0.01142570098903814
    },
    {
      "id": "34",
      "color": 0.008882699918517383,
      "size": 0.02401086397454496
    },
    {
      "id": "35",
      "color": 0.017854342680741774,
      "size": 0.009730706316363438
    },
    {
      "id": "36",
      "color": 0.020249056324259416,
      "size": 0.01752531682984324
    },
    {
      "id": "37",
      "color": 0.007174796473396957,
      "size": 0.007121334331008951
    },
    {
      "id": "38",
      "color": 0.01450132978827943,
      "size": 0.015063661936628524
    },
    {
      "id": "39",
      "color": 0.011199532143236988,
      "size": 0.011364612344687676
    },
    {
      "id": "40",
      "color": 0.00710368413048093,
      "size": 0.006983143922372507
    },
    {
      "id": "41",
      "color": 0.008443418616833311,
      "size": 0.009670613305571523
    },
    {
      "id": "42",
      "color": 0.009330826846265678,
      "size": 0.011555990556027153
    },
    {
      "id": "43",
      "color": 0.00942522771125253,
      "size": 0.008962198131380678
    },
    {
      "id": "44",
      "color": 0.00745155692112404,
      "size": 0.0037840460908174136
    },
    {
      "id": "45",
      "color": 0.006911926531334429,
      "size": 0.004784300409139225
    },
    {
      "id": "46",
      "color": 0.005416065450529544,
      "size": 0.005597693653032948
    },
    {
      "id": "47",
      "color": 0.0039775317257113585,
      "size": 0.004216240335896382
    },
    {
      "id": "48",
      "color": 0.001870443121533265,
      "size": 0.002193838781824499
    },
    {
      "id": "49",
      "color": 0.0014514447086369682,
      "size": 0.0009795084804241475
    },
    {
      "id": "50",
      "color": 0.0,
      "size": 0.0
    }
  ]
}