{
  "links": [
    {
      "source": "11",
      "target": "16"
    },
    {
      "source": "2",
      "target": "51"
    },
    {
      "source": "38",
      "target": "43"
    },
    {
      "source": "50",
      "target": "56"
    },
    {
      "source": "46",
      "target": "25"
    },
    {
      "source": "41",
      "target": "30"
    },
    {
      "source": "17",
      "target": "25"
    },
    {
      "source": "5",
      "target": "23"
    },
    {
      "source": "56",
      "target": "21"
    },
    {
      "source": "31",
      "target": "32"
    },
    {
      "source": "38",
      "target": "37"
    },
    {
      "source": "35",
      "target": "37"
    },
    {
      "source": "37",
      "target": "31"
    },
    {
      "source": "1",
      "target": "25"
    },
    {
      "source": "43",
      "target": "2"
    },
    {
      "source": "29",
      "target": "22"
    },
    {
      "source": "22",
      "target": "7"
    },
    {
      "source": "33",
      "target": "39"
    },
    {
      "source": "19",
      "target": "10"
    },
    {
      "source": "36",
      "target": "31"
    },
    {
      "source": "3",
      "target": "2"
    },
    {
      "source": "29",
      "target": "7"
    },
    {
      "source": "26",
      "target": "21"
    },
    {
      "source": "52",
      "target": "12"
    },
    {
      "source": "17",
      "target": "41"
    },
    {
      "source": "13",
      "target": "15"
    },
    {
      "source": "2",
      "target": "43"
    },
    {
      "source": "33",
      "target": "49"
    },
    {
      "source": "30",
      "target": "43"
    },
    {
      "source": "40",
      "target": "39"
    },
    {
      "source": "37",
      "target": "22"
    },
    {
      "source": "24",
      "target": "11"
    },
    {
      "source": "52",
      "target": "27"
    },
    {
      "source": "43",
      "target": "13"
    },
    {
      "source": "11",
      "target": "7"
    },
    {
      "source": "18",
      "target": "25"
    },
    {
      "source": "41",
      "target": "34"
    },
    {
      "source": "48",
      "target": "30"
    },
    {
      "source": "21",
      "target": "55"
    },
    {
      "source": "41",
      "target": "55"
    }
  ],
  "nodes": [
    {
      "id": "1",
      "color": 0.03916391286088146,
      "size": 0.07151766043428161
    },
    {
      "id": "2",
      "color": 0.0597825869921458,
      "size": 0.04760186246953835
    },
    {
      "id": "3",
      "color": 0.05566721602249301,
      "size": 0.049973929997606505
    },
    {
      "id": "4",
      "color": 0.05459886385193733,
      "size": 0.08672534350968401
    },
    {
      "id": "5",
      "color": 0.0307952196188267,
      "size": 0.04620892545182784
    },
    {
      "id": "6",
      "color": 0.04706633791565027,
      "size": 0.03073263682506791
    },
    {
      "id": "7",
      "color": 0.034850595910809724,
      "size": 0.06228405603909203
    },
    {
      "id": "8",
      "color": 0.06907652210249944,
      "size": 0.04902944794912728
    },
    {
      "id": "9",
      "color": 0.05087304085690344,
      "size": 0.06310189932151489
    },
    {
      "id": "10",
      "color": 0.052922904873368766,
      "size": 0.033455689194320015
    },
    {
      "id": "11",
      "color": 0.035010095405033526,
      "size": 0.0788204861552079
    },
    {
      "id": "12",
      "color": 0.04884413828898858,
      "size": 0.06063811704817208
    },
    {
      "id": "13",
      "color": 0.05401700797756409,
      "size": 0.07321900153947859
    },
    {
      "id": "14",
      "color": 0.047077532203816864,
      "size": 0.04542816232364589
    },
    {
      "id": "15",
      "color": 0.047064447744785666,
      "size": 0.03252079963160959
    },
    {
      "id": "16",
      "color": 0.04133569759027401,
      "size": 0.06565028876889102
    },
    {
      "id": "17",
      "color": 0.034214593164729176,
      "size": 0.029440028373330776
    },
    {
      "id": "18",
      "color": 0.054155882030894026,
      "size": 0.05440514970438769
    },
    {
      "id": "19",
      "color": 0.02292697292605772,
      "size": 0.02193195316201228
    },
    {
      "id": "20",
      "color": 0.0461937854118229,
      "size": 0.023471955170229698
    },
    {
      "id": "21",
      "color": 0.03341213028579046,
      "size": 0.05607011555970732
    },
    {
      "id": "22",
      "color": 0.02531797342011886,
      "size": 0.041847025906842715
    },
    {
      "id": "23",
      "color": 0.05301736197943269,
      "size": 0.04573995362955423
    },
    {
      "id": "24",
      "color": 0.04849743553251672,
      "size": 0.04273018102584794
    },
    {
      "id": "25",
      "color": 0.020079502721638665,
      "size": 0.02053924310771507
    },
    {
      "id": "26",
      "color": 0.039825609263294204,
      "size": 0.05003031054977928
    },
    {
      "id": "27",
      "color": 0.041167315575690915,
      "size": 0.03437028893823985
    },
    {
      "id": "28",
      "color": 0.02175124323356206,
      "size": 0.03575802864046166
    },
    {
      "id": "29",
      "color": 0.03774224077852874,
      "size": 0.01842250595347279
    },
    {
      "id": "30",
      "color": 0.037624231910867736,
      "size": 0.04428981652042169
    },
    {
      "id": "31",
      "color": 0.03353735409458335,
      "size": 0.02654317151291166
    },
    {
      "id": "32",
      "color": 0.03196954221445506,
      "size": 0.03277210750427271
    },
    {
      "id": "33",
      "color": 0.0179831587642087,
      "size": 0.015805225037696966
    },
    {
      "id": "34",
      "color": 0.019706467733310907,
      "size": 0.019248546857428873
    },
    {
      "id": "35",
      "color": 0.031090289058072408,
      "size": 0.022680415681210306
    },
    {
      "id": "36",
      "color": 0.017262413198971007,
      "size": 0.025673976718452556
    },
    {
      "id": "37",
      "color": 0.031769051051525186,
      "size": 0.015446284464608561
    },
    {
      "id": "38",
      "color": 0.01120278199277322,
      "size": 0.020845881677087494
    },
    {
      "id": "39",
      "color": 0.02653347501348074,
      "size": 0.013741482164399575
    },
    {
      "id": "40",
      "color": 0.010085243371046451,
      "size": 0.020549818504461328
    },
    {
      "id": "41",
      "color": 0.022890528739416695,
      "size": 0.012897782555113814
    },
    {
      "id": "42",
      "color": 0.024153491193824185,
      "size": 0.008349428665747954
    },
    {
      "id": "43",
      "color": 0.01722337598762538,
      "size": 0.01224413868478665
    },
    {
      "id": "44",
      "color": 0.01596377415826991,
      "size": 0.018795583711702916
    },
    {
      "id": "45",
      "color": 0.010882283698859936,
      "size": 0.0067103356874645
    },
    {
      "id": "46",
      "color": 0.015787735757838355,
      "size": 0.01656730916228493
    },
    {
      "id": "47",
      "color": 0.014426246405449657,
      "size": 0.01235820827356205
    },
    {
      "id": "48",
      "color": 0.005023030226257634,
      "size": 0.005383781904345014
    },
    {
      "id": "49",
      "color": 0.012319018009272828,
      "size": 0.004440845446644327
    },
    {
      "id": "50",
      "color": 0.004434827346003992,
      "size": 0.00496239190731009
    },
    {
      "id": "51",
      "color": 0.007765220094958114,
      "size": 0.007530806162749712
    },
    {
      "id": "52",
      "color": 0.005445271156027314,
      "size": 0.003587576553802439
    },
    {
      "id": "53",
      "color": 0.004562642623090021,
      "size": 0.003392664211853695
    },
    {
      "id": "54",
      "color": 0.0021862939982987438,
      "size": 0.001577838466291631
    },
    {
      "id": "55",
      "color": 0.0012550656011433804,
      "size": 0.0006550445557800924
    },
    {
      "id": "56",
      "color": 0.0,
      "size": 0.0
    }
  ]
}