{
  "links": [
    {
      "source": "4",
      "target": "10"
    },
    {
      "source": "18",
      "target": "13"
    },
    {
      "source": "17",
      "target": "7"
    },
    {
      "source": "16",
      "target": "9"
    },
    {
      "source": "18",
      "target": "5"
    },
    {
      "source": "9",
      "target": "3"
    },
    {
      "source": "19",
      "target": "17"
    },
    {
      "source": "13",
      "target": "5"
    },
    {
      "source": "20",
      "target": "10"
    },
    {
      "source": "5",
      "target": "20"
    },
    {
      "source": "22",
      "target": "9"
    },
    {
      "source": "5",
      "target": "21"
    },
    {
      "source": "10",
      "target": "22"
    },
    {
      "source": "6",
      "target": "13"
    },
    {
      "source": "4",
      "target": "2"
    },
    {
      "source": "7",
      "target": "2"
    },
    {
      "source": "8",
      "target": "15"
    }
  ],
  "nodes": [
    {
      "id": "1",
      "color": 0.029753303060615053,
      "size": 0.02244804638143727
    },
    {
      "id": "2",
      "color": 0.026527596816610634,
      "size": 0.027111613988843493
    },
    {
      "id": "3",
      "color": 0.022860316781955173,
      "size": 0.02942582119666362
    },
    {
      "id": "4",
      "color": 0.03139018020986722,
      "size": 0.024150630020942226
    },
    {
      "id": "5",
      "color": 0.025212735724162546,
      "size": 0.022814705766324328
    },
    {
      "id": "6",
      "color": 0.026230124638280502,
      "size": 0.021319980789148603
    },
    {
      "id": "7",
      "color": 0.012374585586675193,
      "size": 0.01878139681889819
    },
    {
      "id": "8",
      "color": 0.015034923642518423,
      "size": 0.018443043620579583
    },
    {
      "id": "9",
      "color": 0.020809735560897526,
      "size": 0.013869448192861032
    },
    {
      "id": "10",
      "color": 0.01536876978854752,
      "size": 0.015188666895487288
    },
    {
      "id": "11",
      "color": 0.017098169430877407,
      "size": 0.0209409039384348
    },
    {
      "id": "12",
      "color": 0.012522158248742083,
      "size": 0.011645805157922356
    },
    {
      "id": "13",
      "color": 0.010135512276685712,
      "size": 0.01690665457188375
    },
    {
      "id": "14",
      "color": 0.01510087503851855,
      "size": 0.011084258579426041
    },
    {
      "id": "15",
      "color": 0.0073019574379487116,
      "size": 0.00903375170922884
    },
    {
      "id": "16",
      "color": 0.008606332138464895,
      "size": 0.006145943020801872
    },
    {
      "id": "17",
      "color": 0.005512723412518345,
      "size": 0.0067899229328721045
    },
    {
      "id": "18",
      "color": 0.005849261564478725,
      "size": 0.005593015651894164
    },
    {
      "id": "19",
      "color": 0.002963032772785993,
      "size": 0.0031779957843137687
    },
    {
      "id": "20",
      "color": 0.0026923411121003316,
      "size": 0.002603755529147067
    },
    {
      "id": "21",
      "color": 0.0006766675405111223,
      "size": 0.0016660069487374697
    },
    {
      "id": "22",
      "color": 0.0,
      "size": 0.0
    }
  ]
}