{
  "links": [
    {
      "source": "1",
      "target": "34"
    },
    {
      "source": "51",
      "target": "31"
    },
    {
      "source": "63",
      "target": "61"
    },
    {
      "source": "1",
      "target": "3"
    },
    {
      "source": "70",
      "target": "63"
    },
    {
      "source": "50",
      "target": "49"
    },
    {
      "source": "31",
      "target": "44"
    },
    {
      "source": "10",
      "target": "21"
    },
    {
      "source": "46",
      "target": "65"
    },
    {
      "source": "29",
      "target": "66"
    },
    {
      "source": "58",
      "target": "36"
    },
    {
      "source": "23",
      "target": "26"
    },
    {
      "source": "63",
      "target": "56"
    },
    {
      "source": "27",
      "target": "73"
    },
    {
      "source": "63",
      "target": "64"
    },
    {
      "source": "49",
      "target": "36"
    },
    {
      "source": "37",
      "target": "9"
    },
    {
      "source": "47",
      "target": "27"
    },
    {
      "source": "53",
      "target": "64"
    },
    {
      "source": "61",
      "target": "19"
    },
    {
      "source": "17",
      "target": "28"
    },
    {
      "source": "58",
      "target": "64"
    },
    {
      "source": "43",
      "target": "2"
    },
    {
      "source": "9",
      "target": "54"
    },
    {
      "source": "1",
      "target": "36"
    },
    {
      "source": "16",
      "target": "65"
    },
    {
      "source": "71",
      "target": "30"
    },
    {
      "source": "41",
      "target": "43"
    },
    {
      "source": "36",
      "target": "12"
    },
    {
      "source": "7",
      "target": "28"
    },
    {
      "source": "72",
      "target": "27"
    },
    {
      "source": "2",
      "target": "27"
    },
    {
      "source": "3",
      "target": "27"
    },
    {
      "source": "17",
      "target": "36"
    },
    {
      "source": "30",
      "target": "38"
    },
    {
      "source": "73",
      "target": "59"
    },
    {
      "source": "51",
      "target": "60"
    },
    {
      "source": "34",
      "target": "19"
    },
    {
      "source": "30",
      "target": "67"
    },
    {
      "source": "41",
      "target": "21"
    },
    {
      "source": "23",
      "target": "29"
    },
    {
      "source": "4",
      "target": "49"
    },
    {
      "source": "73",
      "target": "41"
    },
    {
      "source": "34",
      "target": "64"
    },
    {
      "source": "10",
      "target": "59"
    },
    {
      "source": "67",
      "target": "38"
    },
    {
      "source": "60",
      "target": "13"
    },
    {
      "source": "42",
      "target": "55"
    },
    {
      "source": "32",
      "target": "73"
    },
    {
      "source": "26",
      "target": "70"
    },
    {
      "source": "2",
      "target": "36"
    },
    {
      "source": "1",
      "target": "31"
    },
    {
      "source": "64",
      "target": "54"
    },
    {
      "source": "24",
      "target": "40"
    },
    {
      "source": "45",
      "target": "2"
    },
    {
      "source": "27",
      "target": "53"
    },
    {
      "source": "60",
      "target": "10"
    },
    {
      "source": "65",
      "target": "14"
    },
    {
      "source": "48",
      "target": "66"
    },
    {
      "source": "26",
      "target": "31"
    },
    {
      "source": "49",
      "target": "56"
    },
    {
      "source": "17",
      "target": "26"
    },
    {
      "source": "38",
      "target": "26"
    },
    {
      "source": "45",
      "target": "10"
    },
    {
      "source": "24",
      "target": "63"
    },
    {
      "source": "65",
      "target": "63"
    }
  ],
  "nodes": [
    {
      "id": "1",
      "color": 0.06940256575463487,
      "size": 0.04582797708218966
    },
    {
      "id": "2",
      "color": 0.08196275061386268,
      "size": 0.047794736598030345
    },
    {
      "id": "3",
      "color": 0.08638240978660915,
      "size": 0.098687975959393
    },
    {
      "id": "4",
      "color": 0.037721992508244144,
      "size": 0.04595628304791813
    },
    {
      "id": "5",
      "color": 0.03291799180514721,
      "size": 0.06751679330059526
    },
    {
      "id": "6",
      "color": 0.07955150928882275,
      "size": 0.053127213149134433
    },
    {
      "id": "7",
      "color": 0.04447555580606199,
      "size": 0.03330035795652103
    },
    {
      "id": "8",
      "color": 0.08742142140210041,
      "size": 0.06440138670875142
    },
    {
      "id": "9",
      "color": 0.05864226037143836,
      "size": 0.04261497156716722
    },
    {
      "id": "10",
      "color": 0.09023063667360602,
      "size": 0.04694822636851487
    },
    {
      "id": "11",
      "color": 0.03640372499225622,
      "size": 0.03523471006767262
    },
    {
      "id": "12",
      "color": 0.08666786245747597,
      "size": 0.07301589094217013
    },
    {
      "id": "13",
      "color": 0.07127942276000296,
      "size": 0.07168119285521381
    },
    {
      "id": "14",
      "color": 0.07159330006145158,
      "size": 0.06117816251360278
    },
    {
      "id": "15",
      "color": 0.05507822134810715,
      "size": 0.08252845305923807
    },
    {
      "id": "16",
      "color": 0.0775980730482486,
      "size": 0.06520322019247624
    },
    {
      "id": "17",
      "color": 0.032153995572949554,
      "size": 0.037573405062262935
    },
    {
      "id": "18",
      "color": 0.061968373153811505,
      "size": 0.046074624600392924
    },
    {
      "id": "19",
      "color": 0.07348713712365162,
      "size": 0.06443695210354104
    },
    {
      "id": "20",
      "color": 0.041012425913995794,
      "size": 0.07322062597142823
    },
    {
      "id": "21",
      "color": 0.04290211697321336,
      "size": 0.07235164747071476
    },
    {
      "id": "22",
      "color": 0.07032381306184712,
      "size": 0.04076034479351902
    },
    {
      "id": "23",
      "color": 0.035967533786400774,
      "size": 0.06631497514611126
    },
    {
      "id": "24",
      "color": 0.0354317357958338,
      "size": 0.05089010601988636
    },
    {
      "id": "25",
      "color": 0.03022970366148592,
      "size": 0.04992314663884344
    },
    {
      "id": "26",
      "color": 0.06716132561977303,
      "size": 0.06592865315419008
    },
    {
      "id": "27",
      "color": 0.04644375405547706,
      "size": 0.03134242242827701
    },
    {
      "id": "28",
      "color": 0.06264993175126839,
      "size": 0.0385570476661861
    },
    {
      "id": "29",
      "color": 0.061491573830061076,
      "size": 0.040908683985988126
    },
    {
      "id": "30",
      "color": 0.05557560561525871,
      "size": 0.02175615297787376
    },
    {
      "id": "31",
      "color": 0.04389261111516758,
      "size": 0.03301730053144606
    },
    {
      "id": "32",
      "color": 0.023375561901363494,
      "size": 0.03121419976210091
    },
    {
      "id": "33",
      "color": 0.0369247465786148,
      "size": 0.032486892121370736
    },
    {
      "id": "34",
      "color": 0.03152648012820089,
      "size": 0.029129091884795837
    },
    {
      "id": "35",
      "color": 0.04692095882774448,
      "size": 0.03065640192459473
    },
    {
      "id": "36",
      "color": 0.03874786694203238,
      "size": 0.037516395715025054
    },
    {
      "id": "37",
      "color": 0.03382913749967028,
      "size": 0.040942881323677724
    },
    {
      "id": "38",
      "color": 0.019458114272237485,
      "size": 0.019172024183011744
    },
    {
      "id": "39",
      "color": 0.04728590039134427,
      "size": 0.02535968939686791
    },
    {
      "id": "40",
      "color": 0.04545551522061826,
      "size": 0.029707714264616727
    },
    {
      "id": "41",
      "color": 0.020615617127758376,
      "size": 0.045884187442412225
    },
    {
      "id": "42",
      "color": 0.02597264398594175,
      "size": 0.04284358002967068
    },
    {
      "id": "43",
      "color": 0.035968788012887595,
      "size": 0.037435078823446655
    },
    {
      "id": "44",
      "color": 0.03553877155724422,
      "size": 0.031255652800289684
    },
    {
      "id": "45",
      "color": 0.022320216604287218,
      "size": 0.013521608489653471
    },
    {
      "id": "46",
      "color": 0.03662547324893159,
      "size": 0.037783095872177805
    },
    {
      "id": "47",
      "color": 0.037356872979186176,
      "size": 0.030363247837800034
    },
    {
      "id": "48",
      "color": 0.013632621310418046,
      "size": 0.02494873762259901
    },
    {
      "id": "49",
      "color": 0.029021285557626397,
      "size": 0.016767619035902223
    },
    {
      "id": "50",
      "color": 0.01841550992449959,
      "size": 0.031811240777098536
    },
    {
      "id": "51",
      "color": 0.027891926022593737,
      "size": 0.013690690678192468
    },
    {
      "id": "52",
      "color": 0.023612915624264933,
      "size": 0.028775948423449865
    },
    {
      "id": "53",
      "color": 0.027039682506758922,
      "size": 0.01365924137574823
    },
    {
      "id": "54",
      "color": 0.01543260540059056,
      "size": 0.010016710644788996
    },
    {
      "id": "55",
      "color": 0.024992764935559703,
      "size": 0.015103099699183118
    },
    {
      "id": "56",
      "color": 0.019040717461712844,
      "size": 0.010277675239569545
    },
    {
      "id": "57",
      "color": 0.02085363763310929,
      "size": 0.02227884322016645
    },
    {
      "id": "58",
      "color": 0.009514045667808158,
      "size": 0.007572989667687949
    },
    {
      "id": "59",
      "color": 0.009400638546407242,
      "size": 0.01580235433231199
    },
    {
      "id": "60",
      "color": 0.010457050981553704,
      "size": 0.008920573466795291
    },
    {
      "id": "61",
      "color": 0.01407971923320836,
      "size": 0.01722552526701298
    },
    {
      "id": "62",
      "color": 0.0065283484644537565,
      "size": 0.009081059245988276
    },
    {
      "id": "63",
      "color": 0.014367175199129983,
      "size": 0.010192939042748313
    },
    {
      "id": "64",
      "color": 0.00489173800387103,
      "size": 0.0072188786945523884
    },
    {
      "id": "65",
      "color": 0.011468857382023462,
      "size": 0.004735212502568375
    },
    {
      "id": "66",
      "color": 0.00949807623093881,
      "size": 0.007246946668488323
    },
    {
      "id": "67",
      "color": 0.007201269647803422,
      "size": 0.005135444337508812
    },
    {
      "id": "68",
      "color": 0.0065908578740687075,
      "size": 0.005436848577521644
    },
    {
      "id": "69",
      "color": 0.004540375823888114,
      "size": 0.004650450329730348
    },
    {
      "id": "70",
      "color": 0.001874714608643632,
      "size": 0.003975935558454911
    },
    {
      "id": "71",
      "color": 0.0014720732182082212,
      "size": 0.002346300469043978
    },
    {
      "id": "72",
      "color": 0.0009929615411584283,
      "size": 0.0007894185853127825
    },
    {
      "id": "73",
      "color": 0.0,
      "size": 0.0
    }
  ]
}