{
  "links": [
    {
      "source": "11",
      "target": "16"
    },
    {
      "source": "14",
      "target": "10"
    },
    {
      "source": "16",
      "target": "10"
    },
    {
      "source": "15",
      "target": "2"
    },
    {
      "source": "11",
      "target": "5"
    },
    {
      "source": "6",
      "target": "3"
    },
    {
      "source": "1",
      "target": "7"
    },
    {
      "source": "5",
      "target": "3"
    }
  ],
  "nodes": [
    {
      "id": "1",
      "color": 0.041292715157671564,
      "size": 0.04085557878570205
    },
    {
      "id": "2",
      "color": 0.03781136498643288,
      "size": 0.021552233865217367
    },
    {
      "id": "3",
      "color": 0.032224803307034255,
      "size": 0.018364384890818767
    },
    {
      "id": "4",
      "color": 0.016204657287973517,
      "size": 0.02718296370096142
    },
    {
      "id": "5",
      "color": 0.027318612460232886,
      "size": 0.022244920051039858
    },
    {
      "id": "6",
      "color": 0.026075419859253893,
      "size": 0.027965000414004734
    },
    {
      "id": "7",
      "color": 0.02295642628308995,
      "size": 0.02071284345031169
    },
    {
      "id": "8",
      "color": 0.018852653310895053,
      "size": 0.011571961687697816
    },
    {
      "id": "9",
      "color": 0.012722738788353947,
      "size": 0.00889069386854422
    },
    {
      "id": "10",
      "color": 0.01588246665875513,
      "size": 0.013628750933631284
    },
    {
      "id": "11",
      "color": 0.012682442229585266,
      "size": 0.011881124581221236
    },
    {
      "id": "12",
      "color": 0.009137202104606603,
      "size": 0.005450146555587941
    },
    {
      "id": "13",
      "color": 0.005891696704868984,
      "size": 0.005461806576546961
    },
    {
      "id": "14",
      "color": 0.002202500811537439,
      "size": 0.0036412203848686774
    },
    {
      "id": "15",
      "color": 0.0016129567845097712,
      "size": 0.0019053694205107762
    },
    {
      "id": "16",
      "color": 0.0,
      "size": 0.0
    }
  ]
}