{
  "links": [
    {
      "source": "30",
      "target": "3"
    },
    {
      "source": "16",
      "target": "9"
    },
    {
      "source": "32",
      "target": "19"
    },
    {
      "source": "9",
      "target": "8"
    },
    {
      "source": "11",
      "target": "35"
    },
    {
      "source": "36",
      "target": "26"
    },
    {
      "source": "34",
      "target": "25"
    },
    {
      "source": "22",
      "target": "33"
    },
    {
      "source": "18",
      "target": "30"
    },
    {
      "source": "3",
      "target": "17"
    },
    {
      "source": "23",
      "target": "36"
    },
    {
      "source": "32",
      "target": "27"
    },
    {
      "source": "35",
      "target": "25"
    },
    {
      "source": "28",
      "target": "30"
    },
    {
      "source": "36",
      "target": "8"
    },
    {
      "source": "30",
      "target": "28"
    },
    {
      "source": "27",
      "target": "5"
    },
    {
      "source": "35",
      "target": "3"
    },
    {
      "source": "27",
      "target": "13"
    },
    {
      "source": "13",
      "target": "6"
    },
    {
      "source": "22",
      "target": "4"
    },
    {
      "source": "38",
      "target": "25"
    },
    {
      "source": "32",
      "target": "11"
    },
    {
      "source": "37",
      "target": "22"
    },
    {
      "source": "23",
      "target": "38"
    },
    {
      "source": "3",
      "target": "22"
    },
    {
      "source": "37",
      "target": "17"
    },
    {
      "source": "35",
      "target": "30"
    },
    {
      "source": "27",
      "target": "8"
    },
    {
      "source": "10",
      "target": "2"
    }
  ],
  "nodes": [
    {
      "id": "1",
      "color": 0.06939567777237267,
      "size": 0.04957439178457158
    },
    {
      "id": "2",
      "color": 0.08801570507551859,
      "size": 0.08132637320147311
    },
    {
      "id": "3",
      "color": 0.047752971461366735,
      "size": 0.08123819831452361
    },
    {
      "id": "4",
      "color": 0.06488045579112389,
      "size": 0.04682458485782508
    },
    {
      "id": "5",
      "color": 0.03502890214373214,
      "size": 0.046908849303072826
    },
    {
      "id": "6",
      "color": 0.03592414329934997,
      "size": 0.03793642946353595
    },
    {
      "id": "7",
      "color": 0.05577985190863751,
      "size": 0.04078460225653917
    },
    {
      "id": "8",
      "color": 0.043670081147787754,
      "size": 0.05613526791305872
    },
    {
      "id": "9",
      "color": 0.05134666024236395,
      "size": 0.03710457657608823
    },
    {
      "id": "10",
      "color": 0.04212339873921309,
      "size": 0.06728739911590217
    },
    {
      "id": "11",
      "color": 0.04989422886666915,
      "size": 0.0568875394429593
    },
    {
      "id": "12",
      "color": 0.030753933002307554,
      "size": 0.06442982508524114
    },
    {
      "id": "13",
      "color": 0.04767373048553213,
      "size": 0.025138316013228117
    },
    {
      "id": "14",
      "color": 0.05425324953537212,
      "size": 0.039967947803376806
    },
    {
      "id": "15",
      "color": 0.04186611508756034,
      "size": 0.03309820546435185
    },
    {
      "id": "16",
      "color": 0.04509672296562682,
      "size": 0.03417686390996103
    },
    {
      "id": "17",
      "color": 0.04064441126471205,
      "size": 0.027045334914647372
    },
    {
      "id": "18",
      "color": 0.027676533758482783,
      "size": 0.036222380891177665
    },
    {
      "id": "19",
      "color": 0.03459029057887729,
      "size": 0.024901794286549286
    },
    {
      "id": "20",
      "color": 0.04236457575157681,
      "size": 0.041094194233352095
    },
    {
      "id": "21",
      "color": 0.024296124050434926,
      "size": 0.04195251077892996
    },
    {
      "id": "22",
      "color": 0.015178762888143816,
      "size": 0.029785904726862506
    },
    {
      "id": "23",
      "color": 0.03542778792710177,
      "size": 0.023906656821820707
    },
    {
      "id": "24",
      "color": 0.028249135735964805,
      "size": 0.018512171898577706
    },
    {
      "id": "25",
      "color": 0.025946044274221106,
      "size": 0.016823539471351668
    },
    {
      "id": "26",
      "color": 0.016788180949985708,
      "size": 0.01968102207549981
    },
    {
      "id": "27",
      "color": 0.018302546882239833,
      "size": 0.018146894341647356
    },
    {
      "id": "28",
      "color": 0.023321201009733724,
      "size": 0.009174365518441046
    },
    {
      "id": "29",
      "color": 0.008042887243859381,
      "size": 0.019359616979895154
    },
    {
      "id": "30",
      "color": 0.008427297193643206,
      "size": 0.018007412058280964
    },
    {
      "id": "31",
      "color": 0.006477018064108541,
      "size": 0.01721974861538107
    },
    {
      "id": "32",
      "color": 0.00819624790450345,
      "size": 0.006399812751507179
    },
    {
      "id": "33",
      "color": 0.010707601177175547,
      "size": 0.006082268131725736
    },
    {
      "id": "34",
      "color": 0.0036638448477844116,
      "size": 0.0071220318634597
    },
    {
      "id": "35",
      "color": 0.006854035672654579,
      "size": 0.003691411668265765
    },
    {
      "id": "36",
      "color": 0.004040264913747352,
      "size": 0.0036105845198863133
    },
    {
      "id": "37",
      "color": 0.0021059687134615396,
      "size": 0.0011780516550957036
    },
    {
      "id": "38",
      "color": 0.0,
      "size": 0.0
    }
  ]
}