{
  "links": [
    {
      "source": "5",
      "target": "4"
    },
    {
      "source": "3",
      "target": "1"
    },
    {
      "source": "1",
      "target": "4"
    },
    {
      "source": "1",
      "target": "6"
    },
    {
      "source": "4",
      "target": "2"
    },
    {
      "source": "5",
      "target": "3"
    }
  ],
  "nodes": [
    {
      "id": "1",
      "color": 0.010009156641798888,
      "size": 0.003975586032223
    },
    {
      "id": "2",
      "color": 0.005194327141562861,
      "size": 0.004857558968057106
    },
    {
      "id": "3",
      "color": 0.006094687892509737,
      "size": 0.0025918777524668625
    },
    {
      "id": "4",
      "color": 0.0035962135904058197,
      "size": 0.0034311856988765077
    },
    {
      "id": "5",
      "color": 0.0007638812120958467,
      "size": 0.0013234307466392155
    },
    {
      "id": "6",
      "color": 0.0,
      "size": 0.0
    }
  ]
}