{
  "links": [
    {
      "source": "14",
      "target": "5"
    },
    {
      "source": "11",
      "target": "5"
    },
    {
      "source": "2",
      "target": "9"
    },
    {
      "source": "18",
      "target": "5"
    },
    {
      "source": "1",
      "target": "17"
    },
    {
      "source": "17",
      "target": "1"
    },
    {
      "source": "13",
      "target": "5"
    },
    {
      "source": "12",
      "target": "16"
    },
    {
      "source": "14",
      "target": "9"
    },
    {
      "source": "17",
      "target": "14"
    },
    {
      "source": "16",
      "target": "7"
    }
  ],
  "nodes": [
    {
      "id": "1",
      "color": 0.019447959004697455,
      "size": 0.025901509244184998
    },
    {
      "id": "2",
      "color": 0.026195733749517856,
      "size": 0.034410376792657286
    },
    {
      "id": "3",
      "color": 0.017384443926987934,
      "size": 0.029589014103445093
    },
    {
      "id": "4",
      "color": 0.028199850253654228,
      "size": 0.01686203672147843
    },
    {
      "id": "5",
      "color": 0.010733912149545735,
      "size": 0.01855480806091671
    },
    {
      "id": "6",
      "color": 0.012347757240288009,
      "size": 0.015974414919499587
    },
    {
      "id": "7",
      "color": 0.014787406150444011,
      "size": 0.01464812284595337
    },
    {
      "id": "8",
      "color": 0.011322462421629136,
      "size": 0.008966583489741416
    },
    {
      "id": "9",
      "color": 0.017088342380032706,
      "size": 0.020817297291660562
    },
    {
      "id": "10",
      "color": 0.009283907208028767,
      "size": 0.012354135051172917
    },
    {
      "id": "11",
      "color": 0.005479137729399612,
      "size": 0.010355115231438502
    },
    {
      "id": "12",
      "color": 0.006278811898646413,
      "size": 0.005536382095517163
    },
    {
      "id": "13",
      "color": 0.006095829835996568,
      "size": 0.008606374373008343
    },
    {
      "id": "14",
      "color": 0.006384648029909474,
      "size": 0.004743331148402111
    },
    {
      "id": "15",
      "color": 0.005195089179055594,
      "size": 0.002870971619619356
    },
    {
      "id": "16",
      "color": 0.0027025117802897077,
      "size": 0.0021246889833109565
    },
    {
      "id": "17",
      "color": 0.0009484748460040476,
      "size": 0.0010111969511383818
    },
    {
      "id": "18",
      "color": 0.0,
      "size": 0.0
    }
  ]
}