{
  "links": [
    {
      "source": "14",
      "target": "11"
    },
    {
      "source": "13",
      "target": "22"
    },
    {
      "source": "2",
      "target": "14"
    },
    {
      "source": "12",
      "target": "1"
    },
    {
      "source": "12",
      "target": "19"
    },
    {
      "source": "17",
      "target": "2"
    },
    {
      "source": "19",
      "target": "15"
    },
    {
      "source": "7",
      "target": "5"
    },
    {
      "source": "4",
      "target": "3"
    },
    {
      "source": "11",
      "target": "21"
    },
    {
      "source": "8",
      "target": "6"
    },
    {
      "source": "1",
      "target": "11"
    },
    {
      "source": "6",
      "target": "15"
    },
    {
      "source": "12",
      "target": "22"
    },
    {
      "source": "4",
      "target": "11"
    },
    {
      "source": "18",
      "target": "10"
    }
  ],
  "nodes": [
    {
      "id": "1",
      "color": 0.033635988006581366,
      "size": 0.035618577320367585
    },
    {
      "id": "2",
      "color": 0.033234475151441095,
      "size": 0.03284642441854867
    },
    {
      "id": "3",
      "color": 0.022223296614951996,
      "size": 0.01448800082836718
    },
    {
      "id": "4",
      "color": 0.026226864262593574,
      "size": 0.02160345182698436
    },
    {
      "id": "5",
      "color": 0.028704572363507076,
      "size": 0.02271067639143089
    },
    {
      "id": "6",
      "color": 0.015455084529836682,
      "size": 0.022149644808160687
    },
    {
      "id": "7",
      "color": 0.012741244966730736,
      "size": 0.02638957097695864
    },
    {
      "id": "8",
      "color": 0.024929768584855072,
      "size": 0.027981639725980088
    },
    {
      "id": "9",
      "color": 0.023264954433175392,
      "size": 0.01294770040229486
    },
    {
      "id": "10",
      "color": 0.023612845114558086,
      "size": 0.021683835968811918
    },
    {
      "id": "11",
      "color": 0.015427519504209898,
      "size": 0.008575655708829283
    },
    {
      "id": "12",
      "color": 0.018870726496863124,
      "size": 0.016156321837025756
    },
    {
      "id": "13",
      "color": 0.013530467361999124,
      "size": 0.015049653851028444
    },
    {
      "id": "14",
      "color": 0.007164460454761311,
      "size": 0.013677936294690753
    },
    {
      "id": "15",
      "color": 0.009804873804188942,
      "size": 0.014072910715367985
    },
    {
      "id": "16",
      "color": 0.011793941908250085,
      "size": 0.01130187885474642
    },
    {
      "id": "17",
      "color": 0.0035046226753982852,
      "size": 0.007779347224733616
    },
    {
      "id": "18",
      "color": 0.007962236673384374,
      "size": 0.006271705060912758
    },
    {
      "id": "19",
      "color": 0.0031678958939894203,
      "size": 0.004944873080902848
    },
    {
      "id": "20",
      "color": 0.001852567334050734,
      "size": 0.0031040403739857583
    },
    {
      "id": "21",
      "color": 0.0014346070186465804,
      "size": 0.001403547737490713
    },
    {
      "id": "22",
      "color": 0.0,
      "size": 0.0
    }
  ]
}